csv_to_geojson/__init__.py
csv_to_geojson/__main__.py
csv_to_geojson/command_line.py
csv_to_geojson/geojson_transformer.py
csv_to_geojson-0.0.1.dist-info/LICENSE
csv_to_geojson-0.0.1.dist-info/METADATA
csv_to_geojson-0.0.1.dist-info/WHEEL
csv_to_geojson-0.0.1.dist-info/entry_points.txt
csv_to_geojson-0.0.1.dist-info/top_level.txt
csv_to_geojson-0.0.1.dist-info/RECORD
