Metadata-Version: 2.1
Name: csv-to-geojson
Version: 0.0.1
Summary: Converts csv files to geojson points.
Home-page: https://github.com/miquel-vv/csv-to-geojson
Author: Miquel Vande Velde
Author-email: miquel.vandevelde@gmail.com
License: UNKNOWN
Platform: UNKNOWN
Classifier: Programming Language :: Python :: 3
Classifier: License :: OSI Approved :: MIT License
Classifier: Operating System :: OS Independent
Requires-Dist: numpy
Requires-Dist: pandas
Requires-Dist: geojson
